buddiEMP/__init__.py
buddiEMP-0.0.7.dist-info/LICENCE.txt
buddiEMP-0.0.7.dist-info/METADATA
buddiEMP-0.0.7.dist-info/WHEEL
buddiEMP-0.0.7.dist-info/top_level.txt
buddiEMP-0.0.7.dist-info/RECORD
