Metadata-Version: 2.1
Name: buddiEMP
Version: 0.0.7
Summary: Managing Employee details
Home-page: UNKNOWN
Author: Venkata Bhargavi S
Author-email: bhargavi.sikhakolli@gmail.com
License: UNKNOWN
Platform: UNKNOWN
Classifier: Programming Language :: Python :: 3
Classifier: License :: OSI Approved :: MIT License
Classifier: Operating System :: OS Independent
